mca_projen_jsii_example/__init__.py
mca_projen_jsii_example/py.typed
mca_projen_jsii_example/_jsii/__init__.py
mca_projen_jsii_example/_jsii/mca-projen-jsii-example@1.10.1.jsii.tgz
mca_projen_jsii_example-1.10.1.dist-info/LICENSE
mca_projen_jsii_example-1.10.1.dist-info/METADATA
mca_projen_jsii_example-1.10.1.dist-info/WHEEL
mca_projen_jsii_example-1.10.1.dist-info/top_level.txt
mca_projen_jsii_example-1.10.1.dist-info/RECORD
