Metadata-Version: 2.1
Name: mca-projen-jsii-example
Version: 1.10.1
Summary: mca-projen-jsii-example
Home-page: https://github.com/marciocadev/mca-projen-jsii-example.git
Author: Marcio Cruz<marciocadev@gmail.com>
License: Apache-2.0
Project-URL: Source, https://github.com/marciocadev/mca-projen-jsii-example.git
Platform: UNKNOWN
Classifier: Intended Audience :: Developers
Classifier: Operating System :: OS Independent
Classifier: Programming Language :: JavaScript
Classifier: Programming Language :: Python :: 3 :: Only
Classifier: Programming Language :: Python :: 3.7
Classifier: Programming Language :: Python :: 3.8
Classifier: Programming Language :: Python :: 3.9
Classifier: Programming Language :: Python :: 3.10
Classifier: Typing :: Typed
Classifier: Development Status :: 5 - Production/Stable
Classifier: License :: OSI Approved
Requires-Python: ~=3.7
License-File: LICENSE
Requires-Dist: jsii (<2.0.0,>=1.50.0)
Requires-Dist: publication (>=0.0.3)
